{
  "iherb_id": 42939,
  "last_updated": "2026-03-20T09:27:19.098Z",
  "first_scraped": "2026-03-20T09:27:19.098Z",
  "source": "fetch-ai-tags",
  "data": {
    "summary": "Customers highlight: Better sleep, Relaxing taste, Sleepy shortly, Nice taste, Relieves aches, Full energy, Easy to use, Easy to dissolve.",
    "tags": [
      {
        "name": "Better sleep",
        "classification": 0,
        "count": 0
      },
      {
        "name": "Relaxing taste",
        "classification": 0,
        "count": 0
      },
      {
        "name": "Sleepy shortly",
        "classification": 0,
        "count": 0
      },
      {
        "name": "Nice taste",
        "classification": 0,
        "count": 0
      },
      {
        "name": "Relieves aches",
        "classification": 0,
        "count": 0
      },
      {
        "name": "Full energy",
        "classification": 0,
        "count": 0
      },
      {
        "name": "Easy to use",
        "classification": 0,
        "count": 0
      },
      {
        "name": "Easy to dissolve",
        "classification": 0,
        "count": 0
      },
      {
        "name": "No benefits",
        "classification": 2,
        "count": 0
      },
      {
        "name": "Stronger flavor",
        "classification": 2,
        "count": 0
      }
    ],
    "rating": null
  },
  "history": [
    {
      "scraped_at": "2026-03-20T09:27:19.098Z",
      "source": "fetch-ai-tags"
    }
  ]
}
