{
  "iherb_id": 5173,
  "last_updated": "2026-03-20T10:04:51.684Z",
  "first_scraped": "2026-03-20T10:04:51.684Z",
  "source": "fetch-ai-tags",
  "data": {
    "summary": "Customers highlight: Alcohol free, Stomach friendly, Taste balanced, Upset stomach, Natural composition, Hair health, Great benefits, Good digestion.",
    "tags": [
      {
        "name": "Alcohol free",
        "classification": 0,
        "count": 0
      },
      {
        "name": "Stomach friendly",
        "classification": 0,
        "count": 0
      },
      {
        "name": "Taste balanced",
        "classification": 0,
        "count": 0
      },
      {
        "name": "Upset stomach",
        "classification": 0,
        "count": 0
      },
      {
        "name": "Natural composition",
        "classification": 0,
        "count": 0
      },
      {
        "name": "Hair health",
        "classification": 0,
        "count": 0
      },
      {
        "name": "Great benefits",
        "classification": 0,
        "count": 0
      },
      {
        "name": "Good digestion",
        "classification": 0,
        "count": 0
      },
      {
        "name": "Not helpful",
        "classification": 2,
        "count": 0
      },
      {
        "name": "Taste not good",
        "classification": 2,
        "count": 0
      }
    ],
    "rating": null
  },
  "history": [
    {
      "scraped_at": "2026-03-20T10:04:51.684Z",
      "source": "fetch-ai-tags"
    }
  ]
}
