{
  "iherb_id": 70055,
  "last_updated": "2026-03-20T10:01:20.641Z",
  "first_scraped": "2026-03-20T10:01:20.641Z",
  "source": "fetch-ai-tags",
  "data": {
    "summary": "Customers highlight: High absorption, Bioavailability important, Taste good, Easy to take, Shipped immediately, Tasty option, Nice flavor, Cherry taste. Some note: Update after, Effective energy.",
    "tags": [
      {
        "name": "High absorption",
        "classification": 0,
        "count": 0
      },
      {
        "name": "Bioavailability important",
        "classification": 0,
        "count": 0
      },
      {
        "name": "Taste good",
        "classification": 0,
        "count": 0
      },
      {
        "name": "Easy to take",
        "classification": 0,
        "count": 0
      },
      {
        "name": "Shipped immediately",
        "classification": 0,
        "count": 0
      },
      {
        "name": "Tasty option",
        "classification": 0,
        "count": 0
      },
      {
        "name": "Nice flavor",
        "classification": 0,
        "count": 0
      },
      {
        "name": "Cherry taste",
        "classification": 0,
        "count": 0
      },
      {
        "name": "Update after",
        "classification": 1,
        "count": 0
      },
      {
        "name": "Effective energy",
        "classification": 1,
        "count": 0
      }
    ],
    "rating": null
  },
  "history": [
    {
      "scraped_at": "2026-03-20T10:01:20.641Z",
      "source": "fetch-ai-tags"
    }
  ]
}
